betacode_flask_restful_swagger_2/__init__.py
betacode_flask_restful_swagger_2/swagger.py
betacode_flask_restful_swagger_2-0.37.dist-info/METADATA
betacode_flask_restful_swagger_2-0.37.dist-info/RECORD
betacode_flask_restful_swagger_2-0.37.dist-info/WHEEL
betacode_flask_restful_swagger_2-0.37.dist-info/top_level.txt
flask_restful_swagger_2/__init__.py
flask_restful_swagger_2/swagger.py
flask_restful_swagger_2_eapy/__init__.py
flask_restful_swagger_2_eapy/swagger.py
